lightningchart/__init__.py
lightningchart/conf.py
lightningchart/instance.py
lightningchart/charts/__init__.py
lightningchart/charts/bar_chart.py
lightningchart/charts/chart_3d.py
lightningchart/charts/chart_xy.py
lightningchart/charts/container.py
lightningchart/charts/dashboard.py
lightningchart/charts/data_grid.py
lightningchart/charts/funnel_chart.py
lightningchart/charts/gauge_chart.py
lightningchart/charts/map_chart.py
lightningchart/charts/parallel_coordinate_chart.py
lightningchart/charts/pie_chart.py
lightningchart/charts/polar_chart.py
lightningchart/charts/pyramid_chart.py
lightningchart/charts/spider_chart.py
lightningchart/charts/treemap_chart.py
lightningchart/charts/zoom_band_chart.py
lightningchart/series/__init__.py
lightningchart/series/area_range_series.py
lightningchart/series/area_series.py
lightningchart/series/box_series.py
lightningchart/series/box_series_3d.py
lightningchart/series/ellipse_series.py
lightningchart/series/heatmap_grid_series.py
lightningchart/series/heatmap_scrolling_grid_series.py
lightningchart/series/line_series.py
lightningchart/series/line_series_3d.py
lightningchart/series/mesh_model_3d.py
lightningchart/series/parallel_coordinate_series.py
lightningchart/series/point_line_series.py
lightningchart/series/point_line_series_3d.py
lightningchart/series/point_series.py
lightningchart/series/point_series_3d.py
lightningchart/series/polar_area_series.py
lightningchart/series/polar_heatmap_series.py
lightningchart/series/polar_line_series.py
lightningchart/series/polar_point_line_series.py
lightningchart/series/polar_point_series.py
lightningchart/series/polar_polygon_series.py
lightningchart/series/polygon_series.py
lightningchart/series/rectangle_series.py
lightningchart/series/segment_series.py
lightningchart/series/spline_series.py
lightningchart/series/step_series.py
lightningchart/series/surface_grid_series.py
lightningchart/series/surface_scrolling_grid_series.py
lightningchart/series/text_series.py
lightningchart-2.1.1.dist-info/METADATA
lightningchart-2.1.1.dist-info/WHEEL
lightningchart-2.1.1.dist-info/top_level.txt
lightningchart-2.1.1.dist-info/RECORD
